[{"id":1,"email":"syed@gmail.com","password":"$2a$12$IwUIBolNIYJD/LSLz/hDqOESdoBdfnvWf/7hBwVQn6sYnjcIIesMW","firstName":"Syed","lastName":"Arsalan"},{"id":2,"email":"rayyan@gmail.com","password":"$2a$12$gQWzDNHIzkm/FiSLMepNdu3GEB.jqE9VcVaSF4yD50CzvH9JWRy8C","firstName":"Syed","lastName":"Rayyan"},{"id":35,"email":"arsalan@gmail.com","password":"$2a$12$Zmk1G0eV2VdpUq3jm2G89uB83AwvwcLBthSCDzcUHoDcOIXHeuebW","firstName":"Syed","lastName":"Arsalan"},{"id":44,"email":"cavishapart@gmail.com","password":"$2a$12$D.riDpHV2rn9noroiCF2Luk4Z4UogDmE8TMGOIPiQPPXoMEo/FkqK","firstName":"Abbbbbbb","lastName":"Baaaaaaaa"}]